{
    "description": "",
    "code": "",
    "ldc": [],
    "metodos": [
        {
            "nombre": "createContext",
            "description": "",
            "parametros": [
                {
                    "nombre": "?> properties",
                    "description": ""
                },
                {
                    "nombre": "ClassLoader classLoader",
                    "description": ""
                },
                {
                    "nombre": "String contextPath",
                    "description": ""
                },
                {
                    "nombre": "Class<?>[] classesToBeBound",
                    "description": ""
                },
                {
                    "nombre": "Map<String",
                    "description": ""
                }
            ]
        }
    ]
}