{
    "description": "",
    "code": "",
    "ldc": [],
    "constructores": [
        {
            "nombre": "SimpleStyleableLongProperty",
            "descrition": "",
            "parametros": [
                {
                    "nombre": "Object bean",
                    "description": ""
                },
                {
                    "nombre": "Number> cssMetaData",
                    "description": ""
                },
                {
                    "nombre": "CssMetaData<? extends Styleable",
                    "description": ""
                },
                {
                    "nombre": "String name",
                    "description": ""
                },
                {
                    "nombre": "Long initialValue",
                    "description": ""
                }
            ]
        }
    ]
}