{
    "description": "",
    "code": "",
    "ldc": [],
    "constructores": [
        {
            "nombre": "SkinBase",
            "description": "",
            "parametros": [
                {
                    "nombre": "C control",
                    "description": ""
                }
            ]
        }
    ],
    "metodos": [
        {
            "nombre": "computeBaselineOffset",
            "description": "",
            "parametros": [
                {
                    "nombre": "double leftInset",
                    "description": ""
                },
                {
                    "nombre": "double bottomInset",
                    "description": ""
                },
                {
                    "nombre": "double rightInset",
                    "description": ""
                },
                {
                    "nombre": "double topInset",
                    "description": ""
                }
            ]
        },
        {
            "nombre": "computeMaxHeight",
            "description": "",
            "parametros": [
                {
                    "nombre": "double bottomInset",
                    "description": ""
                },
                {
                    "nombre": "double width",
                    "description": ""
                },
                {
                    "nombre": "double topInset",
                    "description": ""
                },
                {
                    "nombre": "double leftInset",
                    "description": ""
                },
                {
                    "nombre": "double rightInset",
                    "description": ""
                }
            ]
        },
        {
            "nombre": "computeMaxWidth",
            "description": "",
            "parametros": [
                {
                    "nombre": "double height",
                    "description": ""
                },
                {
                    "nombre": "double rightInset",
                    "description": ""
                },
                {
                    "nombre": "double topInset",
                    "description": ""
                },
                {
                    "nombre": "double leftInset",
                    "description": ""
                },
                {
                    "nombre": "double bottomInset",
                    "description": ""
                }
            ]
        },
        {
            "nombre": "computeMinHeight",
            "description": "",
            "parametros": [
                {
                    "nombre": "double bottomInset",
                    "description": ""
                },
                {
                    "nombre": "double width",
                    "description": ""
                },
                {
                    "nombre": "double topInset",
                    "description": ""
                },
                {
                    "nombre": "double leftInset",
                    "description": ""
                },
                {
                    "nombre": "double rightInset",
                    "description": ""
                }
            ]
        },
        {
            "nombre": "computeMinWidth",
            "description": "",
            "parametros": [
                {
                    "nombre": "double height",
                    "description": ""
                },
                {
                    "nombre": "double rightInset",
                    "description": ""
                },
                {
                    "nombre": "double topInset",
                    "description": ""
                },
                {
                    "nombre": "double leftInset",
                    "description": ""
                },
                {
                    "nombre": "double bottomInset",
                    "description": ""
                }
            ]
        },
        {
            "nombre": "computePrefHeight",
            "description": "",
            "parametros": [
                {
                    "nombre": "double bottomInset",
                    "description": ""
                },
                {
                    "nombre": "double width",
                    "description": ""
                },
                {
                    "nombre": "double topInset",
                    "description": ""
                },
                {
                    "nombre": "double leftInset",
                    "description": ""
                },
                {
                    "nombre": "double rightInset",
                    "description": ""
                }
            ]
        },
        {
            "nombre": "computePrefWidth",
            "description": "",
            "parametros": [
                {
                    "nombre": "double height",
                    "description": ""
                },
                {
                    "nombre": "double rightInset",
                    "description": ""
                },
                {
                    "nombre": "double topInset",
                    "description": ""
                },
                {
                    "nombre": "double leftInset",
                    "description": ""
                },
                {
                    "nombre": "double bottomInset",
                    "description": ""
                }
            ]
        },
        {
            "nombre": "consumeMouseEvents",
            "description": "",
            "parametros": [
                {
                    "nombre": "boolean value",
                    "description": ""
                }
            ]
        },
        {
            "nombre": "executeAccessibleAction",
            "description": "",
            "parametros": [
                {
                    "nombre": "AccessibleAction action",
                    "description": ""
                },
                {
                    "nombre": "Object... parameters",
                    "description": ""
                }
            ]
        },
        {
            "nombre": "getChildren",
            "description": ""
        },
        {
            "nombre": "getClassCssMetaData",
            "description": ""
        },
        {
            "nombre": "getCssMetaData",
            "description": ""
        },
        {
            "nombre": "layoutChildren",
            "description": "",
            "parametros": [
                {
                    "nombre": "double contentY",
                    "description": ""
                },
                {
                    "nombre": "double contentX",
                    "description": ""
                },
                {
                    "nombre": "double contentHeight",
                    "description": ""
                },
                {
                    "nombre": "double contentWidth",
                    "description": ""
                }
            ]
        },
        {
            "nombre": "layoutInArea",
            "description": "",
            "parametros": [
                {
                    "nombre": "double areaBaselineOffset",
                    "description": ""
                },
                {
                    "nombre": "double areaHeight",
                    "description": ""
                },
                {
                    "nombre": "HPos halignment",
                    "description": ""
                },
                {
                    "nombre": "Insets margin",
                    "description": ""
                },
                {
                    "nombre": "Node child",
                    "description": ""
                },
                {
                    "nombre": "double areaX",
                    "description": ""
                },
                {
                    "nombre": "boolean fillWidth",
                    "description": ""
                },
                {
                    "nombre": "double areaWidth",
                    "description": ""
                },
                {
                    "nombre": "double areaY",
                    "description": ""
                },
                {
                    "nombre": "boolean fillHeight",
                    "description": ""
                },
                {
                    "nombre": "VPos valignment",
                    "description": ""
                }
            ]
        },
        {
            "nombre": "positionInArea",
            "description": "",
            "parametros": [
                {
                    "nombre": "double areaBaselineOffset",
                    "description": ""
                },
                {
                    "nombre": "double areaHeight",
                    "description": ""
                },
                {
                    "nombre": "HPos halignment",
                    "description": ""
                },
                {
                    "nombre": "Insets margin",
                    "description": ""
                },
                {
                    "nombre": "Node child",
                    "description": ""
                },
                {
                    "nombre": "double areaX",
                    "description": ""
                },
                {
                    "nombre": "double areaWidth",
                    "description": ""
                },
                {
                    "nombre": "double areaY",
                    "description": ""
                },
                {
                    "nombre": "VPos valignment",
                    "description": ""
                }
            ]
        },
        {
            "nombre": "pseudoClassStateChanged",
            "description": "",
            "parametros": [
                {
                    "nombre": "boolean active",
                    "description": ""
                },
                {
                    "nombre": "PseudoClass pseudoClass",
                    "description": ""
                }
            ]
        },
        {
            "nombre": "queryAccessibleAttribute",
            "description": "",
            "parametros": [
                {
                    "nombre": "Object... parameters",
                    "description": ""
                },
                {
                    "nombre": "AccessibleAttribute attribute",
                    "description": ""
                }
            ]
        },
        {
            "nombre": "registerChangeListener",
            "description": "",
            "parametros": [
                {
                    "nombre": "ObservableValue<?> property",
                    "description": ""
                },
                {
                    "nombre": "Consumer<ObservableValue<?>> consumer",
                    "description": ""
                }
            ]
        },
        {
            "nombre": "snappedBottomInset",
            "description": ""
        },
        {
            "nombre": "snappedLeftInset",
            "description": ""
        },
        {
            "nombre": "snappedRightInset",
            "description": ""
        },
        {
            "nombre": "snappedTopInset",
            "description": ""
        },
        {
            "nombre": "snapPosition",
            "description": "",
            "parametros": [
                {
                    "nombre": "double value",
                    "description": ""
                }
            ]
        },
        {
            "nombre": "snapPositionX",
            "description": "",
            "parametros": [
                {
                    "nombre": "double value",
                    "description": ""
                }
            ]
        },
        {
            "nombre": "snapPositionY",
            "description": "",
            "parametros": [
                {
                    "nombre": "double value",
                    "description": ""
                }
            ]
        },
        {
            "nombre": "snapSize",
            "description": "",
            "parametros": [
                {
                    "nombre": "double value",
                    "description": ""
                }
            ]
        },
        {
            "nombre": "snapSizeX",
            "description": "",
            "parametros": [
                {
                    "nombre": "double value",
                    "description": ""
                }
            ]
        },
        {
            "nombre": "snapSizeY",
            "description": "",
            "parametros": [
                {
                    "nombre": "double value",
                    "description": ""
                }
            ]
        },
        {
            "nombre": "snapSpace",
            "description": "",
            "parametros": [
                {
                    "nombre": "double value",
                    "description": ""
                }
            ]
        },
        {
            "nombre": "snapSpaceX",
            "description": "",
            "parametros": [
                {
                    "nombre": "double value",
                    "description": ""
                }
            ]
        },
        {
            "nombre": "snapSpaceY",
            "description": "",
            "parametros": [
                {
                    "nombre": "double value",
                    "description": ""
                }
            ]
        },
        {
            "nombre": "unregisterChangeListeners",
            "description": "",
            "parametros": [
                {
                    "nombre": "ObservableValue<?> property",
                    "description": ""
                }
            ]
        }
    ]
}