{
    "description": "",
    "code": "",
    "ldc": [],
    "constructores": [
        {
            "nombre": "SynthComboBoxUI",
            "description": ""
        }
    ],
    "metodos": [
        {
            "nombre": "createUI",
            "description": "",
            "parametros": [
                {
                    "nombre": "JComponent c",
                    "description": ""
                }
            ]
        },
        {
            "nombre": "getDefaultSize",
            "description": ""
        },
        {
            "nombre": "installUI",
            "description": "",
            "parametros": [
                {
                    "nombre": "JComponent c",
                    "description": ""
                }
            ]
        },
        {
            "nombre": "paint",
            "description": "",
            "parametros": [
                {
                    "nombre": "SynthContext context",
                    "description": ""
                },
                {
                    "nombre": "JComponent c",
                    "description": ""
                },
                {
                    "nombre": "Graphics g",
                    "description": ""
                }
            ]
        },
        {
            "nombre": "paintCurrentValue",
            "description": "",
            "parametros": [
                {
                    "nombre": "Rectangle bounds",
                    "description": ""
                },
                {
                    "nombre": "Graphics g",
                    "description": ""
                },
                {
                    "nombre": "boolean hasFocus",
                    "description": ""
                }
            ]
        },
        {
            "nombre": "update",
            "description": "",
            "parametros": [
                {
                    "nombre": "JComponent c",
                    "description": ""
                },
                {
                    "nombre": "Graphics g",
                    "description": ""
                }
            ]
        }
    ]
}