{
    "description": "",
    "code": "",
    "ldc": [],
    "sintaxis": "class DocTestFinder\n",
    "atributos": [],
    "metodos": [
        {
            "nombre": "find",
            "description": "",
            "code": "",
            "ldc": [],
            "sintaxis": "find(obj[, name][, module][, globs][, extraglobs])\n",
            "parametros": [
                {
                    "nombre": "obj[, name][, module][, globs][, extraglobs]",
                    "description": ""
                }
            ]
        }
    ],
    "constructores": [
        {
            "nombre": "DocTestFinder",
            "description": "",
            "code": "",
            "ldc": [],
            "sintaxis": "class doctest.DocTestFinder(verbose=False, parser=DocTestParser(), recurse=True, exclude_empty=True)\n",
            "parametros": [
                {
                    "nombre": "recurse",
                    "description": ""
                },
                {
                    "nombre": "parser",
                    "description": ""
                },
                {
                    "nombre": "exclude_empty",
                    "description": ""
                },
                {
                    "nombre": "verbose",
                    "description": ""
                }
            ]
        }
    ]
}