{
    "description": "",
    "code": "",
    "ldc": [],
    "constructores": [
        {
            "nombre": "EventQueueMonitor",
            "description": ""
        }
    ],
    "metodos": [
        {
            "nombre": "addGUIInitializedListener",
            "description": "",
            "parametros": [
                {
                    "nombre": "GUIInitializedListener l",
                    "description": ""
                }
            ]
        },
        {
            "nombre": "addTopLevelWindowListener",
            "description": "",
            "parametros": [
                {
                    "nombre": "TopLevelWindowListener l",
                    "description": ""
                }
            ]
        },
        {
            "nombre": "eventDispatched",
            "description": "",
            "parametros": [
                {
                    "nombre": "AWTEvent theEvent",
                    "description": ""
                }
            ]
        },
        {
            "nombre": "getAccessibleAt",
            "description": "",
            "parametros": [
                {
                    "nombre": "Point p",
                    "description": ""
                }
            ]
        },
        {
            "nombre": "getCurrentMousePosition",
            "description": ""
        },
        {
            "nombre": "getTopLevelWindows",
            "description": ""
        },
        {
            "nombre": "getTopLevelWindowWithFocus",
            "description": ""
        },
        {
            "nombre": "isGUIInitialized",
            "description": ""
        },
        {
            "nombre": "maybeInitialize",
            "description": ""
        },
        {
            "nombre": "removeGUIInitializedListener",
            "description": "",
            "parametros": [
                {
                    "nombre": "GUIInitializedListener l",
                    "description": ""
                }
            ]
        },
        {
            "nombre": "removeTopLevelWindowListener",
            "description": "",
            "parametros": [
                {
                    "nombre": "TopLevelWindowListener l",
                    "description": ""
                }
            ]
        }
    ]
}