{
    "description": "",
    "code": "",
    "ldc": [],
    "constructores": [
        {
            "nombre": "KeyRep",
            "description": "",
            "parametros": [
                {
                    "nombre": "String algorithm",
                    "description": ""
                },
                {
                    "nombre": "KeyRep.Type type",
                    "description": ""
                },
                {
                    "nombre": "String format",
                    "description": ""
                },
                {
                    "nombre": "byte[] encoded",
                    "description": ""
                }
            ]
        }
    ],
    "metodos": [
        {
            "nombre": "readResolve",
            "description": ""
        }
    ]
}