{
    "description": "",
    "code": "",
    "ldc": [],
    "constructores": [
        {
            "nombre": "BarChart",
            "descrition": "",
            "parametros": [
                {
                    "nombre": "ObservableList<XYChart.Series<X",
                    "description": ""
                },
                {
                    "nombre": "Axis<X> xAxis",
                    "description": ""
                },
                {
                    "nombre": "Y>> data",
                    "description": ""
                },
                {
                    "nombre": "double categoryGap",
                    "description": ""
                },
                {
                    "nombre": "Axis<Y> yAxis",
                    "description": ""
                }
            ]
        }
    ],
    "metodos": [
        {
            "nombre": "barGapProperty",
            "description": ""
        },
        {
            "nombre": "categoryGapProperty",
            "description": ""
        },
        {
            "nombre": "getBarGap",
            "description": ""
        },
        {
            "nombre": "getCategoryGap",
            "description": ""
        },
        {
            "nombre": "getClassCssMetaData",
            "description": ""
        },
        {
            "nombre": "getCssMetaData",
            "description": ""
        },
        {
            "nombre": "setBarGap",
            "description": "",
            "parametros": [
                {
                    "nombre": "double value",
                    "description": ""
                }
            ]
        },
        {
            "nombre": "setCategoryGap",
            "description": "",
            "parametros": [
                {
                    "nombre": "double value",
                    "description": ""
                }
            ]
        }
    ]
}