{
    "description": "",
    "code": "",
    "ldc": [],
    "constructores": [
        {
            "nombre": "BasicScrollPaneUI",
            "description": ""
        }
    ],
    "metodos": [
        {
            "nombre": "createHSBChangeListener",
            "description": ""
        },
        {
            "nombre": "createMouseWheelListener",
            "description": ""
        },
        {
            "nombre": "createPropertyChangeListener",
            "description": ""
        },
        {
            "nombre": "createUI",
            "description": "",
            "parametros": [
                {
                    "nombre": "JComponent x",
                    "description": ""
                }
            ]
        },
        {
            "nombre": "createViewportChangeListener",
            "description": ""
        },
        {
            "nombre": "createVSBChangeListener",
            "description": ""
        },
        {
            "nombre": "getBaseline",
            "description": "",
            "parametros": [
                {
                    "nombre": "JComponent c",
                    "description": ""
                },
                {
                    "nombre": "int width",
                    "description": ""
                },
                {
                    "nombre": "int height",
                    "description": ""
                }
            ]
        },
        {
            "nombre": "getBaselineResizeBehavior",
            "description": "",
            "parametros": [
                {
                    "nombre": "JComponent c",
                    "description": ""
                }
            ]
        },
        {
            "nombre": "getMaximumSize",
            "description": "",
            "parametros": [
                {
                    "nombre": "JComponent c",
                    "description": ""
                }
            ]
        },
        {
            "nombre": "installDefaults",
            "description": "",
            "parametros": [
                {
                    "nombre": "JScrollPane scrollpane",
                    "description": ""
                }
            ]
        },
        {
            "nombre": "installKeyboardActions",
            "description": "",
            "parametros": [
                {
                    "nombre": "JScrollPane c",
                    "description": ""
                }
            ]
        },
        {
            "nombre": "installListeners",
            "description": "",
            "parametros": [
                {
                    "nombre": "JScrollPane c",
                    "description": ""
                }
            ]
        },
        {
            "nombre": "syncScrollPaneWithViewport",
            "description": ""
        },
        {
            "nombre": "uninstallDefaults",
            "description": "",
            "parametros": [
                {
                    "nombre": "JScrollPane c",
                    "description": ""
                }
            ]
        },
        {
            "nombre": "uninstallKeyboardActions",
            "description": "",
            "parametros": [
                {
                    "nombre": "JScrollPane c",
                    "description": ""
                }
            ]
        },
        {
            "nombre": "uninstallListeners",
            "description": "",
            "parametros": [
                {
                    "nombre": "JComponent c",
                    "description": ""
                }
            ]
        },
        {
            "nombre": "updateColumnHeader",
            "description": "",
            "parametros": [
                {
                    "nombre": "PropertyChangeEvent e",
                    "description": ""
                }
            ]
        },
        {
            "nombre": "updateRowHeader",
            "description": "",
            "parametros": [
                {
                    "nombre": "PropertyChangeEvent e",
                    "description": ""
                }
            ]
        },
        {
            "nombre": "updateScrollBarDisplayPolicy",
            "description": "",
            "parametros": [
                {
                    "nombre": "PropertyChangeEvent e",
                    "description": ""
                }
            ]
        },
        {
            "nombre": "updateViewport",
            "description": "",
            "parametros": [
                {
                    "nombre": "PropertyChangeEvent e",
                    "description": ""
                }
            ]
        }
    ],
    "campos": [
        {
            "nombre": "hsbChangeListener",
            "description": ""
        },
        {
            "nombre": "scrollpane",
            "description": ""
        },
        {
            "nombre": "spPropertyChangeListener",
            "description": ""
        },
        {
            "nombre": "viewportChangeListener",
            "description": ""
        },
        {
            "nombre": "vsbChangeListener",
            "description": ""
        }
    ]
}