{
    "description": "",
    "code": "",
    "ldc": [],
    "constructores": [
        {
            "nombre": "UnknownUserExceptionHelper",
            "description": ""
        }
    ],
    "metodos": [
        {
            "nombre": "extract",
            "description": "",
            "parametros": [
                {
                    "nombre": "Any a",
                    "description": ""
                }
            ]
        },
        {
            "nombre": "id",
            "description": ""
        },
        {
            "nombre": "insert",
            "description": "",
            "parametros": [
                {
                    "nombre": "Any a",
                    "description": ""
                },
                {
                    "nombre": "UnknownUserException that",
                    "description": ""
                }
            ]
        },
        {
            "nombre": "read",
            "description": "",
            "parametros": [
                {
                    "nombre": "InputStream istream",
                    "description": ""
                }
            ]
        },
        {
            "nombre": "type",
            "description": ""
        },
        {
            "nombre": "write",
            "description": "",
            "parametros": [
                {
                    "nombre": "UnknownUserException value",
                    "description": ""
                },
                {
                    "nombre": "OutputStream ostream",
                    "description": ""
                }
            ]
        }
    ]
}