{
    "description": "",
    "code": "",
    "ldc": [],
    "constructores": [
        {
            "nombre": "CardTerminals",
            "descrition": ""
        }
    ],
    "metodos": [
        {
            "nombre": "getTerminal",
            "description": "",
            "parametros": [
                {
                    "nombre": "String name",
                    "description": ""
                }
            ]
        },
        {
            "nombre": "list",
            "description": "",
            "parametros": [
                {
                    "nombre": "CardTerminals.State state",
                    "description": ""
                }
            ]
        },
        {
            "nombre": "waitForChange",
            "description": "",
            "parametros": [
                {
                    "nombre": "long timeout",
                    "description": ""
                }
            ]
        }
    ]
}