{
    "description": "",
    "code": "",
    "ldc": [],
    "constructores": [
        {
            "nombre": "ClassValue",
            "descrition": ""
        }
    ],
    "metodos": [
        {
            "nombre": "computeValue",
            "description": "",
            "parametros": [
                {
                    "nombre": "Class<?> type",
                    "description": ""
                }
            ]
        },
        {
            "nombre": "get",
            "description": "",
            "parametros": [
                {
                    "nombre": "Class<?> type",
                    "description": ""
                }
            ]
        },
        {
            "nombre": "remove",
            "description": "",
            "parametros": [
                {
                    "nombre": "Class<?> type",
                    "description": ""
                }
            ]
        }
    ]
}