{
    "description": "",
    "code": "",
    "ldc": [],
    "metodos": [
        {
            "nombre": "getDisplayName",
            "description": "",
            "parametros": [
                {
                    "nombre": "TextStyle style",
                    "description": ""
                },
                {
                    "nombre": "Locale locale",
                    "description": ""
                }
            ]
        },
        {
            "nombre": "getValue",
            "description": ""
        },
        {
            "nombre": "of",
            "description": "",
            "parametros": [
                {
                    "nombre": "int hijrahEra",
                    "description": ""
                }
            ]
        },
        {
            "nombre": "range",
            "description": "",
            "parametros": [
                {
                    "nombre": "TemporalField field",
                    "description": ""
                }
            ]
        },
        {
            "nombre": "valueOf",
            "description": "",
            "parametros": [
                {
                    "nombre": "String name",
                    "description": ""
                }
            ]
        },
        {
            "nombre": "values",
            "description": ""
        }
    ],
    "enumerados": [
        {
            "nombre": "AH",
            "description": ""
        }
    ]
}