{
    "description": "",
    "code": "",
    "ldc": [],
    "constructores": [
        {
            "nombre": "HTMLEditorKit.ParserCallback",
            "description": ""
        }
    ],
    "metodos": [
        {
            "nombre": "flush",
            "description": ""
        },
        {
            "nombre": "handleComment",
            "description": "",
            "parametros": [
                {
                    "nombre": "char[] data",
                    "description": ""
                },
                {
                    "nombre": "int pos",
                    "description": ""
                }
            ]
        },
        {
            "nombre": "handleEndOfLineString",
            "description": "",
            "parametros": [
                {
                    "nombre": "String eol",
                    "description": ""
                }
            ]
        },
        {
            "nombre": "handleEndTag",
            "description": "",
            "parametros": [
                {
                    "nombre": "int pos",
                    "description": ""
                },
                {
                    "nombre": "HTML.Tag t",
                    "description": ""
                }
            ]
        },
        {
            "nombre": "handleError",
            "description": "",
            "parametros": [
                {
                    "nombre": "int pos",
                    "description": ""
                },
                {
                    "nombre": "String errorMsg",
                    "description": ""
                }
            ]
        },
        {
            "nombre": "handleSimpleTag",
            "description": "",
            "parametros": [
                {
                    "nombre": "MutableAttributeSet a",
                    "description": ""
                },
                {
                    "nombre": "int pos",
                    "description": ""
                },
                {
                    "nombre": "HTML.Tag t",
                    "description": ""
                }
            ]
        },
        {
            "nombre": "handleStartTag",
            "description": "",
            "parametros": [
                {
                    "nombre": "MutableAttributeSet a",
                    "description": ""
                },
                {
                    "nombre": "int pos",
                    "description": ""
                },
                {
                    "nombre": "HTML.Tag t",
                    "description": ""
                }
            ]
        },
        {
            "nombre": "handleText",
            "description": "",
            "parametros": [
                {
                    "nombre": "char[] data",
                    "description": ""
                },
                {
                    "nombre": "int pos",
                    "description": ""
                }
            ]
        }
    ],
    "campos": [
        {
            "nombre": "IMPLIED",
            "description": ""
        }
    ]
}