{
    "description": "",
    "code": "",
    "ldc": [],
    "constructores": [
        {
            "nombre": "AbstractJSObject",
            "description": ""
        }
    ],
    "metodos": [
        {
            "nombre": "call",
            "description": "",
            "parametros": [
                {
                    "nombre": "Object thiz",
                    "description": ""
                },
                {
                    "nombre": "Object... args",
                    "description": ""
                }
            ]
        },
        {
            "nombre": "eval",
            "description": "",
            "parametros": [
                {
                    "nombre": "String s",
                    "description": ""
                }
            ]
        },
        {
            "nombre": "getDefaultValue",
            "description": "",
            "parametros": [
                {
                    "nombre": "Class<?> hint",
                    "description": ""
                },
                {
                    "nombre": "JSObject jsobj",
                    "description": ""
                }
            ]
        },
        {
            "nombre": "getMember",
            "description": "",
            "parametros": [
                {
                    "nombre": "String name",
                    "description": ""
                }
            ]
        },
        {
            "nombre": "getSlot",
            "description": "",
            "parametros": [
                {
                    "nombre": "int index",
                    "description": ""
                }
            ]
        },
        {
            "nombre": "hasMember",
            "description": "",
            "parametros": [
                {
                    "nombre": "String name",
                    "description": ""
                }
            ]
        },
        {
            "nombre": "hasSlot",
            "description": "",
            "parametros": [
                {
                    "nombre": "int slot",
                    "description": ""
                }
            ]
        },
        {
            "nombre": "isArray",
            "description": ""
        },
        {
            "nombre": "isFunction",
            "description": ""
        },
        {
            "nombre": "isInstance",
            "description": "",
            "parametros": [
                {
                    "nombre": "Object instance",
                    "description": ""
                }
            ]
        },
        {
            "nombre": "isStrictFunction",
            "description": ""
        },
        {
            "nombre": "keySet",
            "description": ""
        },
        {
            "nombre": "newObject",
            "description": "",
            "parametros": [
                {
                    "nombre": "Object... args",
                    "description": ""
                }
            ]
        },
        {
            "nombre": "removeMember",
            "description": "",
            "parametros": [
                {
                    "nombre": "String name",
                    "description": ""
                }
            ]
        },
        {
            "nombre": "setMember",
            "description": "",
            "parametros": [
                {
                    "nombre": "String name",
                    "description": ""
                },
                {
                    "nombre": "Object value",
                    "description": ""
                }
            ]
        },
        {
            "nombre": "setSlot",
            "description": "",
            "parametros": [
                {
                    "nombre": "Object value",
                    "description": ""
                },
                {
                    "nombre": "int index",
                    "description": ""
                }
            ]
        },
        {
            "nombre": "toNumber",
            "description": ""
        },
        {
            "nombre": "values",
            "description": ""
        }
    ]
}