{
    "description": "",
    "code": "",
    "ldc": [],
    "constructores": [
        {
            "nombre": "Axis.TickMark",
            "description": ""
        }
    ],
    "metodos": [
        {
            "nombre": "getLabel",
            "description": ""
        },
        {
            "nombre": "getPosition",
            "description": ""
        },
        {
            "nombre": "getValue",
            "description": ""
        },
        {
            "nombre": "isTextVisible",
            "description": ""
        },
        {
            "nombre": "labelProperty",
            "description": ""
        },
        {
            "nombre": "positionProperty",
            "description": ""
        },
        {
            "nombre": "setLabel",
            "description": "",
            "parametros": [
                {
                    "nombre": "String value",
                    "description": ""
                }
            ]
        },
        {
            "nombre": "setPosition",
            "description": "",
            "parametros": [
                {
                    "nombre": "double value",
                    "description": ""
                }
            ]
        },
        {
            "nombre": "setTextVisible",
            "description": "",
            "parametros": [
                {
                    "nombre": "boolean value",
                    "description": ""
                }
            ]
        },
        {
            "nombre": "setValue",
            "description": "",
            "parametros": [
                {
                    "nombre": "T v",
                    "description": ""
                }
            ]
        },
        {
            "nombre": "toString",
            "description": ""
        },
        {
            "nombre": "valueProperty",
            "description": ""
        }
    ]
}