{
    "description": "",
    "code": "",
    "ldc": [],
    "constructores": [
        {
            "nombre": "ModelMBeanConstructorInfo",
            "description": "",
            "parametros": [
                {
                    "nombre": "Descriptor descriptor",
                    "description": ""
                },
                {
                    "nombre": "String description",
                    "description": ""
                },
                {
                    "nombre": "MBeanParameterInfo[] signature",
                    "description": ""
                },
                {
                    "nombre": "String name",
                    "description": ""
                },
                {
                    "nombre": "Constructor<?> constructorMethod",
                    "description": ""
                }
            ]
        }
    ],
    "metodos": [
        {
            "nombre": "clone",
            "description": ""
        },
        {
            "nombre": "getDescriptor",
            "description": ""
        },
        {
            "nombre": "setDescriptor",
            "description": "",
            "parametros": [
                {
                    "nombre": "Descriptor inDescriptor",
                    "description": ""
                }
            ]
        },
        {
            "nombre": "toString",
            "description": ""
        }
    ]
}